{
    "name": "Jury",
    "fields": [
        {
            "fieldName": "numjury",
            "fieldType": "Integer"
        }
    ],
    "relationships": [
        {
            "relationshipType": "many-to-many",
            "otherEntityName": "examen",
            "otherEntityRelationshipName": "jury",
            "relationshipName": "examen",
            "otherEntityField": "id",
            "ownerSide": true
        }
    ],
    "changelogDate": "20200404193100",
    "entityTableName": "jury",
    "dto": "no",
    "pagination": "no",
    "service": "no",
    "jpaMetamodelFiltering": false,
    "fluentMethods": true,
    "readOnly": false,
    "embedded": false,
    "clientRootFolder": "",
    "applications": [
        "jhipster"
    ]
}